oarepo_heartbeat/__init__.py
oarepo_heartbeat/libraries.py
oarepo_heartbeat/version.py
oarepo_heartbeat/views.py
oarepo_heartbeat-1.0.3.dist-info/METADATA
oarepo_heartbeat-1.0.3.dist-info/WHEEL
oarepo_heartbeat-1.0.3.dist-info/top_level.txt
oarepo_heartbeat-1.0.3.dist-info/RECORD
