Metadata-Version: 2.1
Name: oarepo-heartbeat
Version: 1.0.3
Summary: UNKNOWN
Home-page: https://github.com/oarepo/oarepo-heartbeat
Author: UCT Prague, CESNET z.s.p.o., NTK
Author-email: miroslav.simek@vscht.cz
License: MIT
Keywords: oarepo invenio flask heartbeat kubernetes
Platform: any
Classifier: Environment :: Web Environment
Classifier: Intended Audience :: Developers
Classifier: License :: OSI Approved :: MIT License
Classifier: Operating System :: OS Independent
Classifier: Programming Language :: Python
Classifier: Topic :: Internet :: WWW/HTTP :: Dynamic Content
Classifier: Topic :: Software Development :: Libraries :: Python Modules
Classifier: Programming Language :: Python :: 2
Classifier: Programming Language :: Python :: 2.7
Classifier: Programming Language :: Python :: 3
Classifier: Programming Language :: Python :: 3.5
Classifier: Programming Language :: Python :: 3.6
Classifier: Development Status :: 3 - Alpha
Requires-Dist: blinker
Requires-Dist: Flask
Requires-Dist: pip (>=6.0.0)
Requires-Dist: importlib-metadata
Provides-Extra: tests
Requires-Dist: oarepo[tests-es7] ; extra == 'tests'
